client/__init__.py
client/main.py
request_forwarder_client-1.1.0.dist-info/licenses/LICENSE
request_forwarder_client-1.1.0.dist-info/METADATA
request_forwarder_client-1.1.0.dist-info/WHEEL
request_forwarder_client-1.1.0.dist-info/entry_points.txt
request_forwarder_client-1.1.0.dist-info/top_level.txt
request_forwarder_client-1.1.0.dist-info/RECORD
