Metadata-Version: 2.4
Name: request-forwarder-client
Version: 1.1.0
Summary: A client for consuming request forwarder server requests
Home-page: https://github.com/avrilfanomar/request-forwarder-client
Author: Andrii Andriichuk
Author-email: andrey000mar@gmail.com
Classifier: Programming Language :: Python :: 3
Classifier: Operating System :: OS Independent
Requires-Python: >=3.6
License-File: LICENSE
Requires-Dist: paho-mqtt
Dynamic: author
Dynamic: author-email
Dynamic: classifier
Dynamic: description
Dynamic: description-content-type
Dynamic: home-page
Dynamic: license-file
Dynamic: requires-dist
Dynamic: requires-python
Dynamic: summary
